eqsolve/__init__.py
eqsolve/equation/__init__.py
eqsolve/equation/contcompound.py
eqsolve/equation/findright.py
eqsolve/equation/intcompound.py
eqsolve/equation/issim.py
eqsolve/equation/midpoint.py
eqsolve/equation/perpint.py
eqsolve/equation/quadsolve.py
eqsolve/equation/slopeint.py
eqsolve/other/__init__.py
eqsolve/other/commands.py
eqsolve/other/help.py
eqsolvcarlover101-2.0.dist-info/METADATA
eqsolvcarlover101-2.0.dist-info/WHEEL
eqsolvcarlover101-2.0.dist-info/top_level.txt
eqsolvcarlover101-2.0.dist-info/RECORD
