Metadata-Version: 2.1
Name: eqsolvcarlover101
Version: 2.0
Summary: Automatic equation solver   -|-   Use import eqsolve
Home-page: https://github.com/Carlover101/equation-solver
Author: Zakkai Thomas
Author-email: zmanmustang2017@gmail.com
Classifier: Programming Language :: Python :: 3.6
Classifier: Programming Language :: Python :: 3.7
Classifier: Programming Language :: Python :: 3.8
Classifier: Programming Language :: Python :: 3.9
Classifier: Programming Language :: Python :: 3.10
Classifier: License :: OSI Approved :: BSD License
Classifier: Operating System :: OS Independent
Requires-Python: >=3.6
